chatendpoint/__init__.py
chatendpoint/chatendpoint.py
chatendpoint-0.4.0.dist-info/DESCRIPTION.rst
chatendpoint-0.4.0.dist-info/METADATA
chatendpoint-0.4.0.dist-info/RECORD
chatendpoint-0.4.0.dist-info/WHEEL
chatendpoint-0.4.0.dist-info/metadata.json
chatendpoint-0.4.0.dist-info/top_level.txt
