Metadata-Version: 2.0
Name: chatendpoint
Version: 0.4.0
Summary: Create custom actions for ChatrHub's automated chat agents. https://chatrhub.com
Home-page: https://github.com/danj565/chatendpoint
Author: ChatrHub INC
Author-email: admin@chatrhub.com
License: MIT license
Keywords: chatendpoint
Platform: UNKNOWN
Classifier: Development Status :: 2 - Pre-Alpha
Classifier: Intended Audience :: Developers
Classifier: License :: OSI Approved :: MIT License
Classifier: Natural Language :: English
Classifier: Programming Language :: Python :: 2
Classifier: Programming Language :: Python :: 2.7
Classifier: Programming Language :: Python :: 3
Classifier: Programming Language :: Python :: 3.4
Classifier: Programming Language :: Python :: 3.5
Classifier: Programming Language :: Python :: 3.6
Requires-Dist: tornado
